aioalfacrm/__init__.py
aioalfacrm/client.py
aioalfacrm/core/__init__.py
aioalfacrm/core/api.py
aioalfacrm/core/auth.py
aioalfacrm/core/entity.py
aioalfacrm/core/entity_manager.py
aioalfacrm/core/exceptions.py
aioalfacrm/core/field.py
aioalfacrm/core/page.py
aioalfacrm/core/paginator.py
aioalfacrm/core/utils.py
aioalfacrm/entities/__init__.py
aioalfacrm/entities/branch.py
aioalfacrm/entities/cgi.py
aioalfacrm/entities/communication.py
aioalfacrm/entities/customer.py
aioalfacrm/entities/customer_tariff.py
aioalfacrm/entities/discount.py
aioalfacrm/entities/group.py
aioalfacrm/entities/lead_reject.py
aioalfacrm/entities/lead_source.py
aioalfacrm/entities/lead_status.py
aioalfacrm/entities/lesson.py
aioalfacrm/entities/lesson_type.py
aioalfacrm/entities/location.py
aioalfacrm/entities/log.py
aioalfacrm/entities/pay.py
aioalfacrm/entities/pay_account.py
aioalfacrm/entities/pay_item.py
aioalfacrm/entities/pay_item_category.py
aioalfacrm/entities/regular_lesson.py
aioalfacrm/entities/room.py
aioalfacrm/entities/study_status.py
aioalfacrm/entities/subject.py
aioalfacrm/entities/tariff.py
aioalfacrm/entities/task.py
aioalfacrm/entities/webhook.py
aioalfacrm/fields/__init__.py
aioalfacrm/fields/bool.py
aioalfacrm/fields/datetime.py
aioalfacrm/fields/dict.py
aioalfacrm/fields/float.py
aioalfacrm/fields/integer.py
aioalfacrm/fields/list.py
aioalfacrm/fields/string.py
aioalfacrm/managers/__init__.py
aioalfacrm/managers/branch.py
aioalfacrm/managers/cgi.py
aioalfacrm/managers/communication.py
aioalfacrm/managers/customer.py
aioalfacrm/managers/customer_tariff.py
aioalfacrm/managers/discount.py
aioalfacrm/managers/group.py
aioalfacrm/managers/lead_reject.py
aioalfacrm/managers/lead_source.py
aioalfacrm/managers/lead_status.py
aioalfacrm/managers/lesson.py
aioalfacrm/managers/lesson_type.py
aioalfacrm/managers/location.py
aioalfacrm/managers/log.py
aioalfacrm/managers/pay.py
aioalfacrm/managers/pay_account.py
aioalfacrm/managers/pay_item.py
aioalfacrm/managers/pay_item_category.py
aioalfacrm-0.3.2.dist-info/LICENSE
aioalfacrm-0.3.2.dist-info/WHEEL
aioalfacrm-0.3.2.dist-info/METADATA
aioalfacrm-0.3.2.dist-info/RECORD
