Metadata-Version: 2.1
Name: aioalfacrm
Version: 0.3.2
Summary: Is an asynchronous implementation for AlfaCRM API
Home-page: https://github.com/stas12312/aioalfacrm
License: MIT
Keywords: aioalfacrm,alfacrm,api,wrapper,asyncio
Author: Stanislav Rush
Author-email: 911rush@gmail.com
Requires-Python: >=3.7,<4.0
Classifier: Framework :: AsyncIO
Classifier: License :: OSI Approved :: MIT License
Classifier: Programming Language :: Python :: 3
Classifier: Programming Language :: Python :: 3.10
Classifier: Programming Language :: Python :: 3.7
Classifier: Programming Language :: Python :: 3.8
Classifier: Programming Language :: Python :: 3.9
Classifier: Typing :: Typed
Requires-Dist: aiohttp (>=3.8.0,<4.0.0)
Project-URL: Repository, https://github.com/stas12312/aioalfacrm
